COPYING
MANIFEST.in
README.rst
setup.cfg
setup.py
bin/synoptic
doc/sample.wsgi
synoptic/__init__.py
synoptic/datamodel.py
synoptic/html.py
synoptic/markdown.py
synoptic/query.py
synoptic.egg-info/PKG-INFO
synoptic.egg-info/SOURCES.txt
synoptic.egg-info/dependency_links.txt
synoptic.egg-info/not-zip-safe
synoptic.egg-info/requires.txt
synoptic.egg-info/top_level.txt
synoptic/schema_ver_repo/__init__.py
synoptic/schema_ver_repo/manage.py
synoptic/schema_ver_repo/migrate.cfg
synoptic/schema_ver_repo/versions/001_Rename_tagset_column.py
synoptic/schema_ver_repo/versions/002_Add_times_and_reminders.py
synoptic/schema_ver_repo/versions/003_Add_all-day_field.py
synoptic/schema_ver_repo/versions/__init__.py
synoptic/static/busy.gif
synoptic/static/calendar-favicon.png
synoptic/static/calendar.css
synoptic/static/calendar.js
synoptic/static/collapse-all.png
synoptic/static/collapsed-hover.png
synoptic/static/collapsed.png
synoptic/static/construction.png
synoptic/static/content.css
synoptic/static/copy.png
synoptic/static/cursor.png
synoptic/static/dragger.png
synoptic/static/edit-clear.png
synoptic/static/error.png
synoptic/static/expand-all.png
synoptic/static/expanded-hover.png
synoptic/static/expanded.png
synoptic/static/export.png
synoptic/static/fullcalendar.css
synoptic/static/fullcalendar.js
synoptic/static/fullcalendar.print.css
synoptic/static/gcal.js
synoptic/static/go-last.png
synoptic/static/history-active.png
synoptic/static/history.png
synoptic/static/inheritance.js
synoptic/static/initial-content.txt
synoptic/static/jquery-migrate.js
synoptic/static/jquery-ui.js
synoptic/static/jquery.bgiframe.js
synoptic/static/jquery.contextmenu.r2.js
synoptic/static/jquery.dimensions.js
synoptic/static/jquery.js
synoptic/static/jquery.timers.js
synoptic/static/jquery.ui.datepicker.js
synoptic/static/json2.js
synoptic/static/main.js
synoptic/static/mobile-calendar.css
synoptic/static/mobile-calendar.js
synoptic/static/mobile.css
synoptic/static/mobile.js
synoptic/static/navbar-bg.png
synoptic/static/print.png
synoptic/static/quit.png
synoptic/static/rsh.js
synoptic/static/sprintf.js
synoptic/static/style.css
synoptic/static/synoptic.png
